simple_udp_proxy/__init__.py
simple_udp_proxy/simple_udp_proxy.py
simple_udp_proxy-0.0.4.dist-info/LICENSE.md
simple_udp_proxy-0.0.4.dist-info/METADATA
simple_udp_proxy-0.0.4.dist-info/WHEEL
simple_udp_proxy-0.0.4.dist-info/top_level.txt
simple_udp_proxy-0.0.4.dist-info/RECORD
