Metadata-Version: 2.1
Name: simple-udp-proxy
Version: 0.0.4
Summary: This package creates a bidirectional bridge between new udp connections to a unique udp port by creating a proxy for each new connection.
Home-page: https://github.com/masoudir/simple_udp_proxy
Author: Masoud Iranmehr
Author-email: masoud.iranmehr@gmail.com
License: UNKNOWN
Platform: UNKNOWN
Classifier: Programming Language :: Python :: 3
Classifier: License :: OSI Approved :: MIT License
Classifier: Operating System :: OS Independent
Requires-Python: >=3.6
